iam_units/__init__.py
iam_units/currency.py
iam_units/emissions.py
iam_units/py.typed
iam_units/test_all.py
iam_units/update.py
iam_units/data/definitions.txt
iam_units/data/emissions/AR4GWP100.txt
iam_units/data/emissions/AR5CCFGWP100.txt
iam_units/data/emissions/AR5GWP100.txt
iam_units/data/emissions/AR6GTP100.txt
iam_units/data/emissions/AR6GWP100.txt
iam_units/data/emissions/AR6GWP20.txt
iam_units/data/emissions/AR6GWP500.txt
iam_units/data/emissions/SARGWP100.txt
iam_units/data/emissions/emissions.txt
iam_units/data/emissions/metrics.txt
iam_units/data/emissions/species.txt
iam_units-2025.10.13.dist-info/licenses/AUTHORS
iam_units-2025.10.13.dist-info/licenses/LICENSE
iam_units-2025.10.13.dist-info/METADATA
iam_units-2025.10.13.dist-info/WHEEL
iam_units-2025.10.13.dist-info/top_level.txt
iam_units-2025.10.13.dist-info/RECORD
