Metadata-Version: 2.4
Name: iam_units
Version: 2025.10.13
Summary: Unit definitions for integrated-assessment research
Author: IAM-units contributors
Maintainer-email: Paul Natsuo Kishimoto <mail@paul.kishimoto.name>
License:                     GNU GENERAL PUBLIC LICENSE
Project-URL: homepage, https://github.com/IAMconsortium/units
Classifier: Intended Audience :: Developers
Classifier: Intended Audience :: Science/Research
Classifier: Operating System :: OS Independent
Classifier: Programming Language :: Python
Classifier: Programming Language :: Python :: 3
Classifier: Programming Language :: Python :: 3.9
Classifier: Programming Language :: Python :: 3.10
Classifier: Programming Language :: Python :: 3.11
Classifier: Programming Language :: Python :: 3.12
Classifier: Programming Language :: Python :: 3.13
Classifier: Topic :: Scientific/Engineering
Classifier: Topic :: Scientific/Engineering :: Information Analysis
Requires-Python: >=3.9
License-File: LICENSE
License-File: AUTHORS
Requires-Dist: pint>=0.24.4
Provides-Extra: update
Requires-Dist: globalwarmingpotentials; extra == "update"
Provides-Extra: tests
Requires-Dist: iam_units[update]; extra == "tests"
Requires-Dist: numpy; extra == "tests"
Requires-Dist: pandas; extra == "tests"
Requires-Dist: pytest; extra == "tests"
Requires-Dist: pytest-cov; extra == "tests"
Dynamic: license-file
